{
	"미 코로나19 환자 110만명 넘겨…주별 경제 재개 속도조절": "http://www.yna.co.kr/view/AKR20200502022900091?section=safe/news",
	"7월 재개 LPGA투어 \"대회 때마다 선수들 코로나19 검사\"": "http://www.yna.co.kr/view/AKR20200502024900007?section=safe/news",
	"일본 아사히신문 '코로나 억제 성공한 대구' 집중 조명": "http://www.yna.co.kr/view/AKR20200502021500073?section=safe/news",
	"아일랜드 다녀온 20대 유학생 확진…인천 누적 95명": "http://www.yna.co.kr/view/AKR20200502022700065?section=safe/news",
	"필리핀서 입국한 10대 코로나19 확진…파주 7번째": "http://www.yna.co.kr/view/AKR20200502021600060?section=safe/news",
	"지구촌나눔운동, 코로나19 미얀마 주민돕기 모금": "http://www.yna.co.kr/view/AKR20200429172000371?section=safe/news",
	"유엔 평화유지군에도 한국산 코로나19 진단키트 공급될 듯": "http://www.yna.co.kr/view/AKR20200502020100072?section=safe/news",
	"아이는 떼쓰는데 나가자니 감염 걱정…'어린이날' 막막한 부모들": "http://www.yna.co.kr/view/AKR20200501035000004?section=safe/news",
	"코로나19 시대 '뉴노멀'…결혼식 밥 안먹고 상가에선 30분 조문": "http://www.yna.co.kr/view/AKR20200501059200017?section=safe/news",
	"[이슈 컷] 마약왕 마스크 쓴 범죄집단, 코로나19에 인기관리 중?": "http://www.yna.co.kr/view/AKR20200429150700797?section=safe/news",
	"FC쾰른에서 코로나19 확진자 3명…독일프로축구 재개 '빨간불'": "http://www.yna.co.kr/view/AKR20200502015000007?section=safe/news",
	"미 식품의약국, 코로나19 치료제로 렘데시비르 긴급사용 승인": "http://www.yna.co.kr/view/AKR20200502012900071?section=safe/news",
	"[특파원 시선] 인니 민심 오토바이 기사들, 코로나 직격탄": "http://www.yna.co.kr/view/AKR20200429194400104?section=safe/news",
	"대구 파견 코로나19 의료진 수당·여비 \"아직도 미지급\"": "http://www.yna.co.kr/view/AKR20200501085800053?section=safe/news",
	"러시아 총리 이어 건설장관도 코로나19 감염…\"병원서 치료\"": "http://www.yna.co.kr/view/AKR20200502012800009?section=safe/news",
	"일본 코로나19 신규 확진 어제 266명…6일째 200명대": "http://www.yna.co.kr/view/AKR20200501099851073?section=safe/news",
	"뉴욕증시, 코로나19로 미·중 충돌 우려…다우, 2.55% 급락 마감": "http://www.yna.co.kr/view/AKR20200502010300009?section=safe/news",
	"브라질, 코로나19에도 축구리그 재개할까…보건부 '긍정 의견'": "http://www.yna.co.kr/view/AKR20200502008700094?section=safe/news",
	"'코로나19 진앙' 미 뉴욕주, 6월 학기말까지 휴교 방침": "http://www.yna.co.kr/view/AKR20200502008300072?section=safe/news",
	"코로나19로 꼬인 북미 공급사슬…미, 멕시코에 \"공장 열라\" 압박": "http://www.yna.co.kr/view/AKR20200502007000087?section=safe/news",
	"마스크 쓴 미 시카고미술관 청동사자…'마스크 도난사고' 수난도": "http://www.yna.co.kr/view/AKR20200502005800009?section=safe/news",
	"아일랜드, 18일부터 코로나19 봉쇄 완화…개학은 9월(종합)": "http://www.yna.co.kr/view/AKR20200502007100085?section=safe/news",
	"커들로 \"중국 코로나19 책임지게 될것…추가관세 트럼프에 달려\"": "http://www.yna.co.kr/view/AKR20200502006500072?section=safe/news",
	"'코로나19 발병시 기업주 배상 책임은'…미 정치권 평행선 공방": "http://www.yna.co.kr/view/AKR20200502006100071?section=safe/news",
	"유럽 각국, 코로나19 정점 시사…봉쇄완화 준비": "http://www.yna.co.kr/view/AKR20200502006000098?section=safe/news",
	"이집트 코로나19 신규 확진 358명으로 하루 최다": "http://www.yna.co.kr/view/AKR20200502005500079?section=safe/news",
	"영국 코로나19 사망자 739명 늘어…총 2만7천510명": "http://www.yna.co.kr/view/AKR20200502004800085?section=safe/news",
	"아일랜드, 코로나19 관련 봉쇄 조치 18일까지 연장": "http://www.yna.co.kr/view/AKR20200502005000091?section=safe/news",
	"미 재무장관, 명문 사립 초중고에 \"코로나19 지원금 반환하라\"": "http://www.yna.co.kr/view/AKR20200502004600072?section=safe/news",
	"WHO \"코로나19 팬데믹, 여전히 국제적 비상사태\"(종합)": "http://www.yna.co.kr/view/AKR20200502002051088?section=safe/news"
}