{
	"\"수도권 남은 코로나 중환자 병상 25개…1주내 소진가능성 높아\"": "http://www.yna.co.kr/view/AKR20201124079300017?section=safe/news",
	"전세계가 지켜보는 코로나와 백신의 전쟁…사령탑은 빌 게이츠": "http://www.yna.co.kr/view/AKR20201124074300009?section=safe/news",
	"코로나 청정지 부산국제금융센터도 뚫렸다…첫 확진자 발생": "http://www.yna.co.kr/view/AKR20201124076600051?section=safe/news",
	"[영상] \"지금 꺾지 않으면\"…거리두기 2단계, 이건 꼭 알아야": "http://www.yna.co.kr/view/AKR20201124077100704?section=safe/news",
	"수도권 오늘부터 2단계 격상…카공族 사라지고 도서관 한산": "http://www.yna.co.kr/view/AKR20201124072600004?section=safe/news",
	"전남 영광 영산선학대학교서 3명 집단감염(종합)": "http://www.yna.co.kr/view/AKR20201124075400054?section=safe/news",
	"민주노총, 코로나19 확산속 내일 총파업 강행…\"방역지침 준수\"": "http://www.yna.co.kr/view/AKR20201124075500530?section=safe/news",
	"매 맞고 코로나까지 감염…미얀마서 강제노동 아동 20여 명 구조": "http://www.yna.co.kr/view/AKR20201124071100076?section=safe/news",
	"경남도, 창원시 거리두기 2단계 격상 검토…나머지 현행 유지": "http://www.yna.co.kr/view/AKR20201124070500052?section=safe/news",
	"[영상] 상하이 공항발 코로나 확진자 잇따라…중국 재확산 시작되나": "http://www.yna.co.kr/view/AKR20201124064000704?section=safe/news",
	"대전시교육청 '사회적 거리두기 2단계 복무지침' 시행": "http://www.yna.co.kr/view/AKR20201124064700063?section=safe/news",
	"거리두기 강화에…백화점 '걱정'·온라인몰 '반사이익'": "http://www.yna.co.kr/view/AKR20201124061600030?section=safe/news",
	"확진자와 동선 겹치는데…학교 방역 두고 교육청·현장 온도 차": "http://www.yna.co.kr/view/AKR20201124065300062?section=safe/news",
	"공주 푸르메요양병원서 15명 코로나19 확진…코호트 격리(종합2보)": "http://www.yna.co.kr/view/AKR20201124043152063?section=safe/news",
	"[속보] \"환자 증가는 수도권이 견인…전국 거리두기 2단계 격상은 일러\"": "http://www.yna.co.kr/view/AKR20201124070600530?section=safe/news",
	"'집단감염' 철원 군부대 2천200명 전수검사 완료…추가확진 없어": "http://www.yna.co.kr/view/AKR20201124068000504?section=safe/news",
	"전북서 코로나19 15명 추가 확진…누적 245명": "http://www.yna.co.kr/view/AKR20201124068700055?section=safe/news",
	"[속보] 정부 \"금주 환자 증가세 유지될 듯…거리두기 효과는 다음주에\"": "http://www.yna.co.kr/view/AKR20201124069600530?section=safe/news",
	"확진 해경 다녀간 유흥업소발 집단감염 확산…16명 추가 양성": "http://www.yna.co.kr/view/AKR20201124064500065?section=safe/news",
	"KB자산운용 직원 확진…여의도 IFC몰 일부 폐쇄": "http://www.yna.co.kr/view/AKR20201124069000002?section=safe/news",
	"서울 어제 133명 신규확진…서초구 아파트발 감염 확산": "http://www.yna.co.kr/view/AKR20201124067700004?section=safe/news",
	"'계약직 강사 확진' 세종시 도담초 원격수업 전환": "http://www.yna.co.kr/view/AKR20201124062100063?section=safe/news",
	"안성서 일가족 3명 확진…자녀 다니는 초교 원격수업 전환": "http://www.yna.co.kr/view/AKR20201124063900061?section=safe/news",
	"경남서 7명 코로나19 추가 확진…노래방·식당서 다수 전파": "http://www.yna.co.kr/view/AKR20201124063500052?section=safe/news",
	"러시아, 코로나 충격 속 공공기관 개혁…유사·중복기능 통합": "http://www.yna.co.kr/view/AKR20201124060200096?section=safe/news",
	"마르티네스, 코로나19 방역 수칙 위반…구단 \"체포되진 않아\"": "http://www.yna.co.kr/view/AKR20201124063300007?section=safe/news",
	"대구서 코로나19 확진 3명 추가": "http://www.yna.co.kr/view/AKR20201124058800053?section=safe/news",
	"워너뮤직, 코로나 대유행 영향 디지털 매출 두자릿수 증가": "http://www.yna.co.kr/view/AKR20201124048800009?section=safe/news",
	"의정부시, 노래방 1주일간 집합금지 명령…최근 9명 확진": "http://www.yna.co.kr/view/AKR20201124059500060?section=safe/news",
	"평창서 해외 입국 20대 인도네시아인 확진…강원 누적 563명": "http://www.yna.co.kr/view/AKR20201124057600062?section=safe/news"
}