{
	"뉴질랜드 신규 확진 83명…\"10여일 더 가파른 증가세 예상\"": "http://www.yna.co.kr/view/AKR20200328026000009?section=safe/news",
	"[속보] 대구 6개 병원 85명 추가 확진…요양병원 1주일 2번 재검": "http://www.yna.co.kr/view/AKR20200328029600053?section=safe/news",
	"미국·유럽 방문 4명 잇따라 양성…인천 확진자 52명(종합)": "http://www.yna.co.kr/view/AKR20200328023951065?section=safe/news",
	"베트남 코로나19 확진 16명 늘어…병원내 감염 잇따라": "http://www.yna.co.kr/view/AKR20200328029100084?section=safe/news",
	"MLB 코레아, 코로나19 극복에 6억원 상당 의료기기 기부": "http://www.yna.co.kr/view/AKR20200328029400007?section=safe/news",
	"[2보] 코로나19, 146명 늘어 총9천478명…대구경북 73명·검역 24명": "http://www.yna.co.kr/view/AKR20200328029200017?section=safe/news",
	"발리 다녀간 한국인 또 코로나19 확진…현지 정보공개 부족": "http://www.yna.co.kr/view/AKR20200328027000104?section=safe/news",
	"김포서 코로나19 완치뒤 일가족 3명 다시 확진": "http://www.yna.co.kr/view/AKR20200328026400065?section=safe/news",
	"[1보] 코로나19 확진자 어제 146명 증가…총 9천478명·사망 144명": "http://www.yna.co.kr/view/AKR20200328028800017?section=safe/news",
	"[속보] 대구 확진자 71명 늘어 총 6천587명…경북 2명 증가": "http://www.yna.co.kr/view/AKR20200327058353053?section=safe/news",
	"코로나19에 허리띠 졸라맨 에어비앤비…마케팅 중단·임금 삭감": "http://www.yna.co.kr/view/AKR20200328027800009?section=safe/news",
	"'코로나19 확산 막자'…충주시, 종댕이길 등 9곳에 행정명령": "http://www.yna.co.kr/view/AKR20200328027200064?section=safe/news",
	"강제징용 사할린 한인들도 모국에 코로나19 성금": "http://www.yna.co.kr/view/AKR20200328016600371?section=safe/news",
	"미국서 입국 20대 대학생 코로나19 확진…전북 11번째": "http://www.yna.co.kr/view/AKR20200328026500055?section=safe/news",
	"미국 코로나19 환자 10만명 돌파…1만명서 8일만에 10배로 폭증(종합2보)": "http://www.yna.co.kr/view/AKR20200328007152091?section=safe/news",
	"영국→세종 입국 40대 남성과 아들 코로나19 확진": "http://www.yna.co.kr/view/AKR20200328025700063?section=safe/news",
	"도쿄 신국립경기장 개장 후 첫 국제육상대회, 코로나19로 연기": "http://www.yna.co.kr/view/AKR20200328025200007?section=safe/news",
	"\"코로나19 여파로 트위터서 중국 혐오 발언 900% 급증\"": "http://www.yna.co.kr/view/AKR20200328024000009?section=safe/news",
	"뉴욕·스위스 방문 2명 양성…인천 코로나19 확진자 52명": "http://www.yna.co.kr/view/AKR20200328023900065?section=safe/news",
	"미국, 코로나19로 봉쇄 늘자 전력소비 감소…휘발유 가격도↓": "http://www.yna.co.kr/view/AKR20200328022500009?section=safe/news",
	"중국 코로나19 신규 확진 54명…모두 해외 입국자": "http://www.yna.co.kr/view/AKR20200328020000083?section=safe/news",
	"내년 최저임금 심의 절차 다음주 시작…최대 변수는 코로나19": "http://www.yna.co.kr/view/AKR20200327155300004?section=safe/news",
	"[증시풍향계] 코로나19 확산세와 주요국 경제지표 주목": "http://www.yna.co.kr/view/AKR20200327162000008?section=safe/news",
	"[팩트체크] 코로나로 문닫은 상인들, 월세감액 제도 없나?": "http://www.yna.co.kr/view/AKR20200327123100502?section=safe/news",
	"코로나19 경북 확진자 2명 증가…완치자는 38명 늘어": "http://www.yna.co.kr/view/AKR20200328022400053?section=safe/news",
	"독일 정부 \"코로나19 검사 한국식으로\"…이제서야 무증상도 검사": "http://www.yna.co.kr/view/AKR20200328012700082?section=safe/news",
	"코로나19 위기국 파견 가는 쿠바 의사들…미국은 \"돈벌이일 뿐\"": "http://www.yna.co.kr/view/AKR20200328016400087?section=safe/news",
	"고글에 방역복까지…기내 감염 우려에 귀국 유학생 '초긴장'": "http://www.yna.co.kr/view/AKR20200327176100004?section=safe/news",
	"미 싱크탱크 웹사이트에 '한국 코로나19 대응사례' 대문글": "http://www.yna.co.kr/view/AKR20200328016200071?section=safe/news",
	"\"확진자 나오면 접촉자만 7일 격리\"…일본야구의 코로나19 대응": "http://www.yna.co.kr/view/AKR20200328018700007?section=safe/news"
}