{
	"줄줄이 코로나 걸린 트럼프 최측근들…오랜 동지 크리스티 입원": "http://www.yna.co.kr/view/AKR20201004026700009?section=safe/news",
	"국내 코로나19 감염 유전자군 발굴…\"신약 개발 발판 기대\"": "http://www.yna.co.kr/view/AKR20201004025100054?section=safe/news",
	"트럼프 코로나 확진에 폼페이오 방한·한미 외교장관회담 연기(종합2보)": "http://www.yna.co.kr/view/AKR20201004020353009?section=safe/news",
	"'틱톡 강제매각' 동력 떨어져…\"트럼프 코로나에 대선 뒤로\"": "http://www.yna.co.kr/view/AKR20201004025500089?section=safe/news",
	"'집단 격리' 부천 요양원서 치매 병실 입소자 6명 확진": "http://www.yna.co.kr/view/AKR20201004024400065?section=safe/news",
	"인천서 할머니 집 방문한 30대 등 4명 코로나19 확진": "http://www.yna.co.kr/view/AKR20201004023100065?section=safe/news",
	"광주·전남 국회의원들이 전하는 추석 민심은…\"코로나19 극복\"": "http://www.yna.co.kr/view/AKR20201004020600054?section=safe/news",
	"추석 연휴 나흘간 서울 일평균 20명 확진…집단감염 계속": "http://www.yna.co.kr/view/AKR20201004022800004?section=safe/news",
	"경남서 코로나19 확진자 1명 추가 발생…미국 다녀온 30대": "http://www.yna.co.kr/view/AKR20201004018900052?section=safe/news",
	"'코로나 입원' 트럼프 동영상에 직접 등장…\"곧 복귀\"(종합2보)": "http://www.yna.co.kr/view/AKR20201004009452009?section=safe/news",
	"코로나19 확진자 대구 2명·경북 4명 추가": "http://www.yna.co.kr/view/AKR20201004020400053?section=safe/news",
	"포천 육군 병사 3명 코로나19 확진…부대 전수조사": "http://www.yna.co.kr/view/AKR20201004021500504?section=safe/news",
	"1년 일정을 3주만에…日 다음달 코로나 치료제 승인 전망": "http://www.yna.co.kr/view/AKR20201004020200073?section=safe/news",
	"경기도, 어제 신규 확진 16명…열흘째 10∼20명대": "http://www.yna.co.kr/view/AKR20201004018200061?section=safe/news",
	"코로나19 신규확진 64명, 연휴 나흘연속 두자리…지역발생 47명(종합)": "http://www.yna.co.kr/view/AKR20201004012951530?section=safe/news",
	"전북서 코로나19 2명 추가 확진…확진자 접촉·폴란드 입국": "http://www.yna.co.kr/view/AKR20201004015600055?section=safe/news",
	"[3보] 코로나19 신규확진 64명, 연휴 나흘연속 두자리…지역발생 47명": "http://www.yna.co.kr/view/AKR20201004012900530?section=safe/news",
	"[속보] 서울·경기 각 16명-인천 6명-부산 5명-경북 4명 등 확진": "http://www.yna.co.kr/view/AKR20201004014900530?section=safe/news",
	"[속보] 코로나19 어제 사망자 1명 늘어 총 421명": "http://www.yna.co.kr/view/AKR20201004014700530?section=safe/news",
	"[2보] 코로나19 어제 64명 신규확진…나흘째 두자릿수, 지역발생 47명": "http://www.yna.co.kr/view/AKR20201004012300530?section=safe/news",
	"[1보] 코로나19 어제 64명 신규확진…나흘째 두자릿수, 지역발생 47명": "http://www.yna.co.kr/view/AKR20201004012000530?section=safe/news",
	"'코로나19 확산'에 부산 만덕동 유치원∼고교 5일부터 원격수업": "http://www.yna.co.kr/view/AKR20201004011400051?section=safe/news",
	"광주서 해외 입국자 1명 코로나19 확진…누적 496명": "http://www.yna.co.kr/view/AKR20201004010900054?section=safe/news",
	"트럼프 코로나 투병중 폼페이오 한국 등 亞순방…관건은 '쿼드'": "http://www.yna.co.kr/view/AKR20201004008400009?section=safe/news",
	"코로나로 빠듯해진 '나라곳간'…충북 수해복구비 33%만 선지급": "http://www.yna.co.kr/view/AKR20200929143100064?section=safe/news",
	"홍삼이 코로나에 특효?…식약처, 허위·과대광고 148건 적발": "http://www.yna.co.kr/view/AKR20200929190400530?section=safe/news",
	"코로나로 벼랑끝 내몰린 극장가…관객·매출 70% 곤두박질": "http://www.yna.co.kr/view/AKR20201003046700001?section=safe/news",
	"코로나19 적자 누적…청주 시내버스 40% 감축 운행": "http://www.yna.co.kr/view/AKR20200929050400064?section=safe/news",
	"브라질 코로나19 누적 확진 500만 코앞…지방선거 비상": "http://www.yna.co.kr/view/AKR20201004007000094?section=safe/news",
	"코로나19가 만든 新예능, 비대면 음악추리 '방콕떼창단'": "http://www.yna.co.kr/view/AKR20200929044600005?section=safe/news"
}