{
	"'해외 입국' 주한미군 또 코로나19 확진…누적 확진자 98명": "http://www.yna.co.kr/view/AKR20200720100800504?section=safe/news",
	"서울서 산발적 감염 잇따라…사무실 이어 요양시설서도 확진자": "http://www.yna.co.kr/view/AKR20200720099100530?section=safe/news",
	"코로나19 위기에 제주 관광경제 vs 방역 '딜레마'": "http://www.yna.co.kr/view/AKR20200720096600056?section=safe/news",
	"[속보] 국내 확진자 42%는 50대 이상…9%는 산소·중증 치료 받아": "http://www.yna.co.kr/view/AKR20200720094900530?section=safe/news",
	"횡성축협 서울역에서 시민에게 마스크 4천장 제공": "http://www.yna.co.kr/view/AKR20200720092600062?section=safe/news",
	"\"코로나 우려\" 보성군, 공공시설 운영 중단 29일까지 연장": "http://www.yna.co.kr/view/AKR20200720091600054?section=safe/news",
	"[속보] 역삼동V빌딩-한화생명, '강남구 사무실' 감염으로 분류…총 24명": "http://www.yna.co.kr/view/AKR20200720092500530?section=safe/news",
	"[속보] 서울 관악구 사무실 관련 1명 추가 확진…누적 33명": "http://www.yna.co.kr/view/AKR20200720091500530?section=safe/news",
	"도쿄 코로나 신규 확진 168명…이틀 연속 100명대로 줄어": "http://www.yna.co.kr/view/AKR20200720090700073?section=safe/news",
	"'휴가철 코로나 걱정 NO'…경남도, '비대면' 관광태세 구축": "http://www.yna.co.kr/view/AKR20200720082000052?section=safe/news",
	"인도 신규 확진 4만명 돌파…17일 만에 하루 감염자 2배 '폭증'": "http://www.yna.co.kr/view/AKR20200720085000077?section=safe/news",
	"제넥신·와이바이오로직스, 코로나19 치료제 공동개발 협약": "http://www.yna.co.kr/view/AKR20200720080400017?section=safe/news",
	"전자출입명부 13만곳 설치…접촉자 추적에 QR코드 1천784건 활용": "http://www.yna.co.kr/view/AKR20200720073900530?section=safe/news",
	"청주 22·23번째 코로나19 확진 스웨덴 국적자 퇴원": "http://www.yna.co.kr/view/AKR20200720071500064?section=safe/news",
	"호주 멜버른 코로나19 재확산으로 \"마스크 없이 외출 금지\"": "http://www.yna.co.kr/view/AKR20200720072300093?section=safe/news",
	"서울 강서구 요양시설서 9명 확진…이용자 등 90여명 검사(종합)": "http://www.yna.co.kr/view/AKR20200720063551004?section=safe/news",
	"정부 \"코로나19와의 긴 싸움 계속…경험 바탕으로 장기전 대비\"": "http://www.yna.co.kr/view/AKR20200720070100530?section=safe/news",
	"미국 자가격리 서명 거부한 부부 전자발찌·가택 연금": "http://www.yna.co.kr/view/AKR20200720052700009?section=safe/news",
	"\"결과 받는데 9일\"…미 코로나19 검사 '무용지물' 경보음": "http://www.yna.co.kr/view/AKR20200720064900075?section=safe/news",
	"코로나 급증에 놀란 일본, 뒤늦게 호스트클럽 단속 방침": "http://www.yna.co.kr/view/AKR20200720067200073?section=safe/news",
	"코로나 이후 뉴욕 명물된 센트럴파크 무료 이발사": "http://www.yna.co.kr/view/AKR20200720057300009?section=safe/news",
	"서울 강서구 요양시설서 확진자 9명 발생…93명 검사": "http://www.yna.co.kr/view/AKR20200720063500004?section=safe/news",
	"코로나19 대구 2명·경북 1명 추가…해외 유입 사례": "http://www.yna.co.kr/view/AKR20200720062000053?section=safe/news",
	"[속보] 서울 강서구 요양시설서 확진자 9명 발생": "http://www.yna.co.kr/view/AKR20200720059700004?section=safe/news",
	"신규확진 26명중 지역발생 4명…73일만에 최소(종합)": "http://www.yna.co.kr/view/AKR20200720032251530?section=safe/news",
	"코로나에 중국 내 명품 매출 급증…\"해외 못 나가 국내 소비\"": "http://www.yna.co.kr/view/AKR20200720052800083?section=safe/news",
	"'코로나19 봉쇄' 능사 아니다?…영국 당국 \"암으로 더 죽는다\"": "http://www.yna.co.kr/view/AKR20200720042800009?section=safe/news",
	"[2보] 신규확진 26명중 지역발생 4명…73일만에 최소": "http://www.yna.co.kr/view/AKR20200720032200530?section=safe/news",
	"중국 신장 코로나19 대규모 감염 우려…신규 확진 17명": "http://www.yna.co.kr/view/AKR20200720048000083?section=safe/news",
	"日중고교, 코로나에 졸업식 교가 취소하고 기미가요는 제창": "http://www.yna.co.kr/view/AKR20200720045900073?section=safe/news"
}