{
	"미 코로나19 연일 확산에도…커들로 \"경제 V자형 회복\" 낙관": "http://www.yna.co.kr/view/AKR20200727124800009?section=safe/news",
	"'위험한 조합' 코로나19와 폭염…취약층 또 한 번 위기": "http://www.yna.co.kr/view/AKR20200727128700009?section=safe/news",
	"이란 보건부 \"전국이 코로나19 '빨간불'\" 경고": "http://www.yna.co.kr/view/AKR20200727132200111?section=safe/news",
	"서울시청서 코로나19 확진자 발생…11층 폐쇄(종합)": "http://www.yna.co.kr/view/AKR20200727129152004?section=safe/news",
	"[2보] 서울시청서 코로나19 확진자 발생…11층 폐쇄": "http://www.yna.co.kr/view/AKR20200727129151004?section=safe/news",
	"[1보] 서울시청서 확진자 발생…1개 층 폐쇄": "http://www.yna.co.kr/view/AKR20200727129100004?section=safe/news",
	"터키 코로나19 신규 확진 13일째 900명대…누적 22만6천명": "http://www.yna.co.kr/view/AKR20200727128400108?section=safe/news",
	"코로나19 2차 확산 광주, 자가격리자 생필품 후원 물품 소진": "http://www.yna.co.kr/view/AKR20200727124400054?section=safe/news",
	"인도네시아 마나도서 한국인 남성 코로나 감염…누적 3명째": "http://www.yna.co.kr/view/AKR20200727115200104?section=safe/news",
	"코로나19로 갈 곳 잃은 헌혈버스…\"주차장에 덩그러니\"": "http://www.yna.co.kr/view/AKR20200727120900063?section=safe/news",
	"싱가포르서 36분 내 코로나 진단법 개발…\"기존의 4분의 1\"": "http://www.yna.co.kr/view/AKR20200727121200076?section=safe/news",
	"[특징주] '코로나19 치료제 관련주' 줄줄이 급락(종합)": "http://www.yna.co.kr/view/AKR20200727054051002?section=safe/news",
	"\"코로나19로 상처받은 대구 치유하자\" 대구시 화상토론 개최": "http://www.yna.co.kr/view/AKR20200727105700053?section=safe/news",
	"도쿄 코로나 신규 확진 131명…7월 감염자 5천명 넘어": "http://www.yna.co.kr/view/AKR20200727110200073?section=safe/news",
	"정은경 \"코로나19 3대 위험요인 세계적유행-여름휴가-고위험군\"": "http://www.yna.co.kr/view/AKR20200727107500530?section=safe/news",
	"하버드 의대 연구진 \"신종 코로나, 후각 뉴런 공격 못 한다\"": "http://www.yna.co.kr/view/AKR20200727109400009?section=safe/news",
	"순창군, 코로나19 확산 우려에 '순창 장류축제' 취소": "http://www.yna.co.kr/view/AKR20200727102900055?section=safe/news",
	"해외유입발 지역감염 확산…러 선박→수리공→동거인 '3차 전파'(종합)": "http://www.yna.co.kr/view/AKR20200726043151530?section=safe/news",
	"\"마스크 쓰라\"는 버스 기사에 몽둥이질…미국 곳곳서 갈등": "http://www.yna.co.kr/view/AKR20200727098400009?section=safe/news",
	"대한적십자사, 코로나로 발 묶인 아프리카인에 검사비용 지원": "http://www.yna.co.kr/view/AKR20200727096900054?section=safe/news",
	"코로나19로 중단된 '필리핀 불법 수출 쓰레기' 국내 반입 재개": "http://www.yna.co.kr/view/AKR20200727090200061?section=safe/news",
	"귀국 이라크 근로자 1명 추가 확진 총 76명…수도권 감염 지속": "http://www.yna.co.kr/view/AKR20200727094800530?section=safe/news",
	"[속보] 서울 관악구 사무실 관련 1명 추가 확진…누적 38명": "http://www.yna.co.kr/view/AKR20200727091700530?section=safe/news",
	"[속보] 서울 강서중앙데이케어센터 관련 3명 추가 확진…누적 28명": "http://www.yna.co.kr/view/AKR20200727091600530?section=safe/news",
	"[속보] 이라크서 귀국 건설근로자 1명 추가 확진…누적 76명": "http://www.yna.co.kr/view/AKR20200727091500530?section=safe/news",
	"북한 \"탈북민 월북사태로 코로나 위험 커져…개성 방역 총력전\"(종합)": "http://www.yna.co.kr/view/AKR20200727043251504?section=safe/news",
	"문화체육관광 분야 코로나 피해 7조원 넘겨…관광업만 5.9조원": "http://www.yna.co.kr/view/AKR20200727082900005?section=safe/news",
	"정부 \"외국인 확진자 치료비 청구, 방역상황 보며 단계적 적용\"": "http://www.yna.co.kr/view/AKR20200727078600530?section=safe/news",
	"32명 확진 러 어선 수리업체 근로자 241명 중 220명 음성": "http://www.yna.co.kr/view/AKR20200727080900051?section=safe/news",
	"필리핀 마닐라, 코로나19 준봉쇄령 다시 발령하나": "http://www.yna.co.kr/view/AKR20200727077900084?section=safe/news"
}