{
	"전주 거주 50대 코로나19 확진…전북 117번째": "http://www.yna.co.kr/view/AKR20200923185700055?section=safe/news",
	"네덜란드 \"코로나19 2차 유행…주간 확진자 가장 많아\"": "http://www.yna.co.kr/view/AKR20200923184800098?section=safe/news",
	"오스트리아 소비자단체 \"당국 코로나 늑장대처\"…민사소송": "http://www.yna.co.kr/view/AKR20200923183500088?section=safe/news",
	"[팩트체크] 말라리아치료제 피라맥스, 코로나에 효능 입증됐나?": "http://www.yna.co.kr/view/AKR20200923144300502?section=safe/news",
	"\"올해 2월 이후 실직한 노동자 100명 중 5명은 코로나19 영향\"": "http://www.yna.co.kr/view/AKR20200923183100530?section=safe/news",
	"전남 코로나19 확진자 1명 추가…해외 입국자": "http://www.yna.co.kr/view/AKR20200923183000054?section=safe/news",
	"오늘 서울 확진자 32명 늘어…누계 5천88명": "http://www.yna.co.kr/view/AKR20200923182700004?section=safe/news",
	"포항서 코로나19 확진자 1명 추가…누계 80명": "http://www.yna.co.kr/view/AKR20200923179100053?section=safe/news",
	"양천구 중학교서 학생 확진자 발생…서울 등교재개 후 첫 사례": "http://www.yna.co.kr/view/AKR20200923179400530?section=safe/news",
	"올해 3∼6월 독감환자 크게 감소…\"코로나19 방역 부수효과\"": "http://www.yna.co.kr/view/AKR20200923173800530?section=safe/news",
	"프랑스 파리에도 코로나19 추가 제한조치 내려진다": "http://www.yna.co.kr/view/AKR20200923177100081?section=safe/news",
	"장호원노인주간보호센터 관련 4명 추가 확진…누적 27명(종합)": "http://www.yna.co.kr/view/AKR20200923123351061?section=safe/news",
	"日 '아비간' 개발사 \"내달 중 코로나 치료제 승인 신청\"": "http://www.yna.co.kr/view/AKR20200923174200073?section=safe/news",
	"부산 자가격리자가 왜 순천 장례식장에…자가격리 관리 허점": "http://www.yna.co.kr/view/AKR20200923169400051?section=safe/news",
	"자가격리 예산 60대 코로나19 확진…아내는 지난 11일 확진": "http://www.yna.co.kr/view/AKR20200923169900063?section=safe/news",
	"보성군, 추석연휴 대비 코로나19 예방 홍보물품 배부": "http://www.yna.co.kr/view/AKR20200923168400054?section=safe/news",
	"\"아동·청소년 코로나 치명률 성인보다 9배 낮아\"…이유는?": "http://www.yna.co.kr/view/AKR20200923148200009?section=safe/news",
	"마약·폭발물 찾던 탐지견, 코로나 19 감염자도 가려낼까": "http://www.yna.co.kr/view/AKR20200923155600009?section=safe/news",
	"시진핑 \"냉전·전면전 벌일 생각없어…코로나 정치화는 안 돼\"(종합3보)": "http://www.yna.co.kr/view/AKR20200923002152072?section=safe/news",
	"'인간과 접촉한 동물 겁을 잃는다'…포식자 방어 본능 급감": "http://www.yna.co.kr/view/AKR20200923161800009?section=safe/news",
	"이스라엘 코로나19 누적 확진자 20만 넘어…한달새 10만 급증": "http://www.yna.co.kr/view/AKR20200923163200079?section=safe/news",
	"인천서 30대 부부, 초등생 딸 이어 확진": "http://www.yna.co.kr/view/AKR20200923165000065?section=safe/news",
	"코로나19 영향 신도수 3배 껑충 뛴 러 신흥종교 교주 체포": "http://www.yna.co.kr/view/AKR20200923158900096?section=safe/news",
	"가톨릭대 부천성모병원 직원 확진…병동 10층 자체 임시폐쇄(종합)": "http://www.yna.co.kr/view/AKR20200923148951065?section=safe/news",
	"용인시청사 지하 1층 출입구 발열체크 직원 확진": "http://www.yna.co.kr/view/AKR20200923155500061?section=safe/news",
	"수원 안전통합센터 관제요원 확진…근무자 45명 이동금지 조치": "http://www.yna.co.kr/view/AKR20200923152100061?section=safe/news",
	"가톨릭대 부천성모병원 직원 확진…환자 10여명 접촉": "http://www.yna.co.kr/view/AKR20200923148900065?section=safe/news",
	"\"미국에 수입된 중국산 KN95 마스크 70% 기준 미달\"": "http://www.yna.co.kr/view/AKR20200923139000009?section=safe/news",
	"코이카, 코로나19 페루 취약계층 지원": "http://www.yna.co.kr/view/AKR20200923145900371?section=safe/news",
	"정은경, '가장 영향력 있는 100인' 선정에 \"코로나 극복에 최선\"": "http://www.yna.co.kr/view/AKR20200923143200530?section=safe/news"
}