{
	"경기 어제 188명 확진…안성 축산물공판장서 사흘새 66명 감염": "http://www.yna.co.kr/view/AKR20210309055300061?section=safe/news",
	"울산 코로나 확진자 19명 발생…사우나발 하루 새 17명 추가": "http://www.yna.co.kr/view/AKR20210309053000057?section=safe/news",
	"백신접종 이상반응 936건 추가 총 4천851건…사망신고 누적 13명": "http://www.yna.co.kr/view/AKR20210309053400530?section=safe/news",
	"충주 코로나19 1차 대응요원 11일까지 백신 접종": "http://www.yna.co.kr/view/AKR20210309052000064?section=safe/news",
	"경매 중단 부산공동어시장 확진자 속출…5명 추가": "http://www.yna.co.kr/view/AKR20210309040900051?section=safe/news",
	"신규확진 446명,휴일효과 사라지자 다시 400명대…집단감염 확산(종합)": "http://www.yna.co.kr/view/AKR20210309032751530?section=safe/news",
	"평창서 병문안 통해 일가족 등 11명 코로나19 확진": "http://www.yna.co.kr/view/AKR20210309049900062?section=safe/news",
	"부산진구의회, 마스크 계약 문제 삼아 구청직원 8명 경찰 고발": "http://www.yna.co.kr/view/AKR20210309045800051?section=safe/news",
	"수도권 임시 검사소서 65명 확진…수도권 지역발생의 21.7%": "http://www.yna.co.kr/view/AKR20210309049700530?section=safe/news",
	"서울서 102명 신규 확진…전날보다 2명 많아": "http://www.yna.co.kr/view/AKR20210309048000004?section=safe/news",
	"'코로나19 때문에' 강릉 경포벚꽃잔치 2년 연속 취소": "http://www.yna.co.kr/view/AKR20210309046800062?section=safe/news",
	"[3보] 신규확진 446명,휴일효과 사라지자 다시 400명대…집단감염 확산": "http://www.yna.co.kr/view/AKR20210309032700530?section=safe/news",
	"삼척시 외국인 노동자 175명 코로나19 무료 전수검사": "http://www.yna.co.kr/view/AKR20210309046100062?section=safe/news",
	"[속보] 코로나19 백신 어제 6만4천111명 접종…11일간 총 38만3천346명": "http://www.yna.co.kr/view/AKR20210309046300530?section=safe/news",
	"[속보] 경기 188명-서울 102명-광주 33명-충북 21명-인천 20명 등 확진": "http://www.yna.co.kr/view/AKR20210309032900530?section=safe/news",
	"태국, 내달부터 코로나19 백신 접종자 격리 7일로 줄듯": "http://www.yna.co.kr/view/AKR20210309045000076?section=safe/news",
	"[속보] 백신접종 이상반응 936건 추가 총 4천851건…사망신고 누적 13건": "http://www.yna.co.kr/view/AKR20210309046200530?section=safe/news",
	"[2보] 코로나19 어제 446명 신규확진…다시 400명대로": "http://www.yna.co.kr/view/AKR20210309032600530?section=safe/news",
	"[속보] 코로나19로 어제 3명 사망…누적 1천645명": "http://www.yna.co.kr/view/AKR20210309032800530?section=safe/news",
	"[1보] 코로나19 어제 446명 신규확진…다시 400명대로": "http://www.yna.co.kr/view/AKR20210309032400530?section=safe/news",
	"정총리 \"거리두기 조정안 신중히 결정하겠다\"": "http://www.yna.co.kr/view/AKR20210309038300001?section=safe/news",
	"J리그 감바 오사카서 코로나19 추가 확진…팀 활동 다시 중단": "http://www.yna.co.kr/view/AKR20210309040700007?section=safe/news",
	"오늘부터 요양병원 중증환자 등 접촉면회 부분 허용": "http://www.yna.co.kr/view/AKR20210309035500530?section=safe/news",
	"일본야구, 미입국 외국인선수에 '발동동'…\"합동격리훈련\" 제안": "http://www.yna.co.kr/view/AKR20210309034400007?section=safe/news",
	"WHO, 코로나19 '백신여권' 반대…\"윤리·실용적 문제\"": "http://www.yna.co.kr/view/AKR20210309030700009?section=safe/news",
	"\"시노백·AZ 백신, 브라질 아마조나스발 변이 바이러스에 효과\"": "http://www.yna.co.kr/view/AKR20210309030000094?section=safe/news",
	"대구서 중구 일가족 관련 등 3명 추가 확진": "http://www.yna.co.kr/view/AKR20210309030100053?section=safe/news",
	"미 CDC \"백신접종자, 저위험 비접종자와 마스크 없이 만나도 돼\"(종합)": "http://www.yna.co.kr/view/AKR20210309004951091?section=safe/news",
	"광주 콜센터 관련 자가격리자 31명 추가 확진…누적 111명": "http://www.yna.co.kr/view/AKR20210309027400054?section=safe/news",
	"경북 확진자 2명 추가…상주·예천 1명씩": "http://www.yna.co.kr/view/AKR20210309028300053?section=safe/news"
}