{
	"태국 교민사회 \"서로 돕고 나누면서 코로나19 함께 극복해요\"": "http://www.yna.co.kr/view/AKR20200404060700076?section=safe/news",
	"<뉴욕증시 주간전망> 유가·실업 주시…코로나19 여전히 관건": "http://www.yna.co.kr/view/AKR20200405005900009?section=safe/news",
	"브라질 코로나19 대응, 빈곤문제에 발목…마땅한 대책 없어 막막": "http://www.yna.co.kr/view/AKR20200405005400094?section=safe/news",
	"국제 가스가격도 사상 최저…코로나발 수요감소에 공급과잉까지": "http://www.yna.co.kr/view/AKR20200404040100003?section=safe/news",
	"WSJ \"코로나19 위기 영웅은 보건 당국자\"…정은경 본부장 호평": "http://www.yna.co.kr/view/AKR20200405005100072?section=safe/news",
	"이탈리아 봉쇄령 5월 중순 풀린다?…\"코로나19와 공존 준비해야\"(종합)": "http://www.yna.co.kr/view/AKR20200404060851109?section=safe/news",
	"코로나19 직격탄 서비스업…\"만회할 수 없는 타격 우려\"": "http://www.yna.co.kr/view/AKR20200404065500002?section=safe/news",
	"\"미국 코로나19 의료시스템 붕괴 수준…병원이 진원지되고 있어\"": "http://www.yna.co.kr/view/AKR20200404012600075?section=safe/news",
	"코로나19 혈장치료 효과보려면 \"완치자 혈액 기증·확보가 관건\"": "http://www.yna.co.kr/view/AKR20200404052900017?section=safe/news",
	"중동 코로나19 확진 7만명 넘어…증가율은 내림세(종합)": "http://www.yna.co.kr/view/AKR20200404061351111?section=safe/news",
	"일본 코로나19 확진 368명 늘어 4천209명…닷새 연속 최다": "http://www.yna.co.kr/view/AKR20200405003700073?section=safe/news",
	"미국 코로나19 환자 30만명 넘어…사흘 만에 10만명 급증(종합)": "http://www.yna.co.kr/view/AKR20200405002351091?section=safe/news",
	"브라질, 코로나19 사망자 431명으로 늘어…확진자는 1만명 넘어": "http://www.yna.co.kr/view/AKR20200405003500094?section=safe/news",
	"키신저 \"코로나19 팬데믹, 세계 질서 영원히 바꿔놓을 것\"": "http://www.yna.co.kr/view/AKR20200405003200072?section=safe/news",
	"유럽 코로나19 확진 60만명에 사망 4만6천명…봉쇄조치 연장": "http://www.yna.co.kr/view/AKR20200405003100085?section=safe/news",
	"이집트 코로나19 확진 1천명 넘어…대박물관 개관 연기": "http://www.yna.co.kr/view/AKR20200405002900079?section=safe/news",
	"프랑스 코로나19 사망자 7천560명…확진자는 6만8천605명": "http://www.yna.co.kr/view/AKR20200405003000085?section=safe/news",
	"\"브라질 코로나19 환자 2주내 4만1천명으로 늘것…최악땐 6만명\"": "http://www.yna.co.kr/view/AKR20200405001900094?section=safe/news",
	"미국 코로나19 환자 30만명 육박…전세계 감염자 4분의1": "http://www.yna.co.kr/view/AKR20200405002300091?section=safe/news",
	"영국 코로나19 사망자 하루새 708명 증가…총 4천313명(종합)": "http://www.yna.co.kr/view/AKR20200404067251085?section=safe/news",
	"이탈리아 신규 확진자 사흘 만에 증가세…중환자는 첫 감소": "http://www.yna.co.kr/view/AKR20200405001800109?section=safe/news",
	"남편 보란 듯?…멜라니아 \"모두 마스크 착용 심각히 여겨야\"": "http://www.yna.co.kr/view/AKR20200405001400071?section=safe/news",
	"\"유로존 구제기금, 코로나19 지원에 320조원까지 제공 가능\"": "http://www.yna.co.kr/view/AKR20200405000700098?section=safe/news",
	"카타르서 입국한 20대 코로나19 확진…광주 27번째": "http://www.yna.co.kr/view/AKR20200405000900054?section=safe/news",
	"\"마스크착용 권고 발표 직전까지 백악관-CDC 충돌 엎치락뒤치락\"": "http://www.yna.co.kr/view/AKR20200405000400071?section=safe/news",
	"스페인 코로나19 사망자 809명↑…\"비상사태 26일까지 연장\"(종합2보)": "http://www.yna.co.kr/view/AKR20200404061752085?section=safe/news",
	"코로나19 신규확진 34% 해외유입…고강도 사회적 거리두기 연장": "http://www.yna.co.kr/view/AKR20200404066900017?section=safe/news",
	"영국 코로나19 사망자 하루새 708명 증가…총 4천313명": "http://www.yna.co.kr/view/AKR20200404067200085?section=safe/news",
	"이탈리아 총리 경호원도 코로나19 감염 사망…총리는 음성": "http://www.yna.co.kr/view/AKR20200404066400109?section=safe/news",
	"서울아산병원서 코로나19 두번째 확진…같은 병실 환아 보호자(종합)": "http://www.yna.co.kr/view/AKR20200404065051017?section=safe/news"
}