{
	"서울 어제 신규확진 42명…언론사 집단감염도 확산(종합)": "http://www.yna.co.kr/view/AKR20201104082251004?section=safe/news",
	"정부 \"코로나 치료제 개발 임상시험 안전…환자 참여-지원 필요\"": "http://www.yna.co.kr/view/AKR20201104084000530?section=safe/news",
	"은성수·조성욱 '코로나 검사' 문자…정무위 조기 산회": "http://www.yna.co.kr/view/AKR20201104088000001?section=safe/news",
	"'집단감염' 안양 노인보호시설 관련 3명 추가 확진": "http://www.yna.co.kr/view/AKR20201104084600061?section=safe/news",
	"서울 어제 신규확진 42명…다중이용시설·모임서 확산": "http://www.yna.co.kr/view/AKR20201104082200004?section=safe/news",
	"창원서 일가족 5명 확진…고교생 아들 양성 후 전 가족 감염(종합)": "http://www.yna.co.kr/view/AKR20201104049151052?section=safe/news",
	"PGA 투어 힉스, 코로나19 양성 반응…휴스턴오픈 불참": "http://www.yna.co.kr/view/AKR20201104076400007?section=safe/news",
	"코로나 극복 머리맞댄 주호영-안철수…보궐선거 논의는 \"고민\"": "http://www.yna.co.kr/view/AKR20201104068700001?section=safe/news",
	"프랑스·멕시코서 입국한 인천 거주자 2명 확진 판정": "http://www.yna.co.kr/view/AKR20201104071400065?section=safe/news",
	"코로나19로 멈췄던 현대차 아산공장 엔진조립라인 조업 재개": "http://www.yna.co.kr/view/AKR20201104067100063?section=safe/news",
	"홍천서 25번째 코로나19 확진자 발생…강원 285명": "http://www.yna.co.kr/view/AKR20201104065600062?section=safe/news",
	"中카슈가르 코로나 무증상감염 116명 추가…주민 반복검사": "http://www.yna.co.kr/view/AKR20201104062200097?section=safe/news",
	"천안서 코로나19 2명 추가…평택 감염자 접촉 등": "http://www.yna.co.kr/view/AKR20201104063700063?section=safe/news",
	"서울 강남구, 확진자 다녀간 업소에 최대 400만원 지원": "http://www.yna.co.kr/view/AKR20201104062300004?section=safe/news",
	"경기도 어제 신규확진 43명…병원·요양시설 산발감염 지속": "http://www.yna.co.kr/view/AKR20201104059500061?section=safe/news",
	"신규확진 118명 사흘만에 다시 세자릿수…핼러윈 영향 여부 주목(종합)": "http://www.yna.co.kr/view/AKR20201104052800530?section=safe/news",
	"경남 창원서 일가족 5명 확진…도 \"감염경로 파악 중\"": "http://www.yna.co.kr/view/AKR20201104049100052?section=safe/news",
	"\"OPEC+ 코로나19 재확산에 예정된 증산 연기 추진\"": "http://www.yna.co.kr/view/AKR20201104047300009?section=safe/news",
	"[3보] 신규확진 118명 사흘만에 다시 세자릿수…핼러윈 영향 여부 주목": "http://www.yna.co.kr/view/AKR20201104031400530?section=safe/news",
	"[속보] 코로나19 어제 사망자 2명 늘어 총 474명": "http://www.yna.co.kr/view/AKR20201104045600530?section=safe/news",
	"[2보] 코로나19 118명 신규확진, 사흘 만에 다시 세자릿수…지역 98명": "http://www.yna.co.kr/view/AKR20201104031300530?section=safe/news",
	"[1보] 코로나19 118명 신규확진, 사흘 만에 다시 세자릿수…지역 98명": "http://www.yna.co.kr/view/AKR20201104031200530?section=safe/news",
	"아산서 코로나19 5명 추가…일가족 등 4명은 부산 결혼식장 참석": "http://www.yna.co.kr/view/AKR20201104041200063?section=safe/news",
	"중대본 \"방심하면 코로나19 폭발적 증가 가능한 위기 상황\"": "http://www.yna.co.kr/view/AKR20201104044100530?section=safe/news",
	"영국·프랑스, 코로나19 하루 사망자 반년만에 최다": "http://www.yna.co.kr/view/AKR20201104036300009?section=safe/news",
	"확진자 두 차례 나온 부산항 러 선박서 또 선원 1명 확진": "http://www.yna.co.kr/view/AKR20201104041500051?section=safe/news",
	"대구서 코로나19 신규 확진자 2명 늘어": "http://www.yna.co.kr/view/AKR20201104041700053?section=safe/news",
	"진천서 태국 국적 40대 코로나19 확진…충북 누적 194명": "http://www.yna.co.kr/view/AKR20201104038600064?section=safe/news",
	"코로나19로 임시 중단 부산창업카페 온라인으로 재개": "http://www.yna.co.kr/view/AKR20201104030500051?section=safe/news",
	"경북서 해외유입 코로나19 확진자 2명 추가": "http://www.yna.co.kr/view/AKR20201104028600053?section=safe/news"
}