{
	"트럼프 \"모더나 코로나19 백신 승인\"": "http://www.yna.co.kr/view/AKR20201218167100098?section=safe/news",
	"[속보] 트럼프 \"미국, 모더나 백신 승인\"<AFP>": "http://www.yna.co.kr/view/AKR20201218166900098?section=safe/news",
	"'집단감염' 경기 요양시설 3곳서 병상 대기중 5명 사망(종합3보)": "http://www.yna.co.kr/view/AKR20201218049353061?section=safe/news",
	"EU 회원국 백신 접종 동시 시작 가능할까…일부 이탈 예고": "http://www.yna.co.kr/view/AKR20201218166100098?section=safe/news",
	"입원-전원 대기중 사망한 코로나19 환자 6명…병상대란 시작됐나(종합)": "http://www.yna.co.kr/view/AKR20201218160051530?section=safe/news",
	"日, 코로나 신규확진 2천800명대…내년 2월 백신 접종 개시": "http://www.yna.co.kr/view/AKR20201218165700073?section=safe/news",
	"병원·요양시설로 번지는 코로나19…충북 22명 추가 확진(종합)": "http://www.yna.co.kr/view/AKR20201218140951064?section=safe/news",
	"남양주, 별내 노인요양시설 관련 3명 추가 확진…누적 43명": "http://www.yna.co.kr/view/AKR20201218165100060?section=safe/news",
	"이재명, 코로나19 검사서 음성 판정…가족은 결과 안 나와": "http://www.yna.co.kr/view/AKR20201218164600061?section=safe/news",
	"부천서 확진자 가족 등 22명 코로나19 추가 양성(종합)": "http://www.yna.co.kr/view/AKR20201218136051065?section=safe/news",
	"의정부 신곡동 학원발 확진자 사흘간 9명…시의회도 영향": "http://www.yna.co.kr/view/AKR20201218163100060?section=safe/news",
	"경주서 7명 확진…5일장 노점상 영업금지": "http://www.yna.co.kr/view/AKR20201218162200053?section=safe/news",
	"강원, 스키장발 '3차감염' 학교까지…동해병원 7명 양성(종합)": "http://www.yna.co.kr/view/AKR20201218097551062?section=safe/news",
	"오늘 오후 6시까지 581명 확진…어제 동시간 대비 73명 줄어": "http://www.yna.co.kr/view/AKR20201218160900530?section=safe/news",
	"울산 코로나19 확진자 9명 추가 발생…사망자는 누적 14명(종합2보)": "http://www.yna.co.kr/view/AKR20201218042252057?section=safe/news",
	"MBC 코로나19 확진자 발생에 주말 예능 6개 결방(종합)": "http://www.yna.co.kr/view/AKR20201218133651005?section=safe/news",
	"당국 \"12월 들어 입원-전원 대기중 사망한 코로나19 확진자 6명\"": "http://www.yna.co.kr/view/AKR20201218160000530?section=safe/news",
	"MBC 예능 조연출·외부 카메라감독 코로나19 확진(종합)": "http://www.yna.co.kr/view/AKR20201218062051005?section=safe/news",
	"당진시, '예배후 함께 식사' 대규모 확진 나음교회 고발": "http://www.yna.co.kr/view/AKR20201218159500063?section=safe/news",
	"오늘 오후 6시까지 서울 145명 신규 확진": "http://www.yna.co.kr/view/AKR20201218160300004?section=safe/news",
	"동해병원 한 병실서 환자·보호자 7명 확진…코호트 격리(종합)": "http://www.yna.co.kr/view/AKR20201218123651062?section=safe/news",
	"17명 살해 이탈리아 희대의 연쇄살인마 코로나19로 옥중 사망": "http://www.yna.co.kr/view/AKR20201218158800109?section=safe/news",
	"[속보] 정부 \"12월 들어 입원-전원 대기중 사망한 코로나19 확진자 6명\"": "http://www.yna.co.kr/view/AKR20201218157900530?section=safe/news",
	"인천서 공무원 1명 포함 46명 확진…32명은 산발적 감염(종합)": "http://www.yna.co.kr/view/AKR20201218072951065?section=safe/news",
	"식약처, 화이자 코로나19 백신 사전검토 착수": "http://www.yna.co.kr/view/AKR20201218154300017?section=safe/news",
	"김포서 4명 코로나19 확진…2명은 감염경로 불명": "http://www.yna.co.kr/view/AKR20201218154700065?section=safe/news",
	"유럽의약품청, 모더나 백신 평가 회의도 1월 6일로 앞당겨 개최": "http://www.yna.co.kr/view/AKR20201218153800098?section=safe/news",
	"교황 \"빈국들 코로나19 백신 혜택에서 배제돼선 안돼\" 호소(종합)": "http://www.yna.co.kr/view/AKR20201218001351109?section=safe/news",
	"사회복지시설 '코호트 수준 격리'…전남도, 행정명령": "http://www.yna.co.kr/view/AKR20201218151500054?section=safe/news",
	"대전서 3명 코로나19 추가 확진…누적 691명째": "http://www.yna.co.kr/view/AKR20201218149500063?section=safe/news"
}