{
	"부천서 35명 확진…태권도학원·어린이집 관련 5명 추가": "http://www.yna.co.kr/view/AKR20210918046600065?section=safe/news",
	"울산 35명 신규 확진…문중 벌초 관련 새 집단감염 확인(종합)": "http://www.yna.co.kr/view/AKR20210918027451057?section=safe/news",
	"오후 6시까지 전국서 1천570명 확진…어제보다 73명 적어": "http://www.yna.co.kr/view/AKR20210918046200530?section=safe/news",
	"[속보] 오후 6시까지 전국서 1천570명 확진…어제보다 73명 적어": "http://www.yna.co.kr/view/AKR20210918045700530?section=safe/news",
	"오후 6시까지 서울 578명 확진…전날보다 19명↑": "http://www.yna.co.kr/view/AKR20210918045500004?section=safe/news",
	"충북 6개 시군서 30명 산발 확진…감염경로 불명 다수": "http://www.yna.co.kr/view/AKR20210918045300064?section=safe/news",
	"스페이스X 관광객들, 톰 크루즈에 \"우주 경험 공유합니다\"": "http://www.yna.co.kr/view/AKR20210918043600009?section=safe/news",
	"경남 23명 신규 확진…백신 접종 1차 70.4%, 2차 42.8%(종합)": "http://www.yna.co.kr/view/AKR20210918034251052?section=safe/news",
	"코로나 자가격리 푸틴, 온라인으로 총선 투표…교외 관저서": "http://www.yna.co.kr/view/AKR20210918042300080?section=safe/news",
	"정부세종청사 국세청 직원 1명 코로나19 확진…긴급 방역": "http://www.yna.co.kr/view/AKR20210918040400530?section=safe/news",
	"추석연휴 첫날 광주서 13명 추가 확진…1차 접종률 69.1%": "http://www.yna.co.kr/view/AKR20210918039500054?section=safe/news",
	"구미서 외국인 농장근로자 집단감염…이틀새 20명": "http://www.yna.co.kr/view/AKR20210918039300053?section=safe/news",
	"이스라엘, 부스터샷 접종 300만명 넘어…국민 3명 중 1명꼴": "http://www.yna.co.kr/view/AKR20210918038700079?section=safe/news",
	"사흘간 백신 이상반응 1만2천703건↑…사망 32명↑인과성 미확인(종합)": "http://www.yna.co.kr/view/AKR20210918025951530?section=safe/news",
	"1차접종 3천607만5천26명, 인구의 70.3%…남은 백신 1천643만회분(종합)": "http://www.yna.co.kr/view/AKR20210918023551530?section=safe/news",
	"부산 해운대 그림전시회·수영구 마사지업소발 집단감염 지속": "http://www.yna.co.kr/view/AKR20210918035300051?section=safe/news",
	"직장-건설현장-목욕탕 등서 새 집단발병…감염경로 '조사중' 37.4%": "http://www.yna.co.kr/view/AKR20210918035500530?section=safe/news",
	"인도, 하루에만 2천100만명에 백신 접종": "http://www.yna.co.kr/view/AKR20210918034500077?section=safe/news",
	"경남 22명 신규 확진…백신 접종 1차 70.4%, 2차 42.8%": "http://www.yna.co.kr/view/AKR20210918034200052?section=safe/news",
	"전북도 \"명절 거리두기 완화는 가족 만나라는 것…방심은 금물\"": "http://www.yna.co.kr/view/AKR20210918032900055?section=safe/news",
	"강릉 공군부대 6명 추가 확진·총 11명…외출·휴가 잠정중단": "http://www.yna.co.kr/view/AKR20210918030100504?section=safe/news",
	"캄보디아, 어린이도 코로나 백신 접종…6∼11세 대상": "http://www.yna.co.kr/view/AKR20210918030600084?section=safe/news",
	"오세훈 시장, 추석연휴 첫날 코로나 대응 점검(종합)": "http://www.yna.co.kr/view/AKR20210917167651004?section=safe/news",
	"'추석 연휴인데'…인천 덕적도서 주민 8명 첫 감염": "http://www.yna.co.kr/view/AKR20210918028300065?section=safe/news",
	"울산 20명 신규 확진…문중 벌초 관련 새 집단감염 확인": "http://www.yna.co.kr/view/AKR20210918027400057?section=safe/news",
	"일본, 코로나 검역 목적 '입국자 시설격리' 줄인다": "http://www.yna.co.kr/view/AKR20210918027500073?section=safe/news",
	"전북서 연휴 첫날 13명 확진…\"대안학교 추가 감염은 없어\"": "http://www.yna.co.kr/view/AKR20210918026800055?section=safe/news",
	"서울 703명 신규 확진…가락시장 집단감염 누적 244명(종합)": "http://www.yna.co.kr/view/AKR20210918023051004?section=safe/news",
	"충북 밤새 19명 확진…음성 소재 인력업체 연쇄감염 누적 20명": "http://www.yna.co.kr/view/AKR20210918025400064?section=safe/news",
	"사흘간 백신 이상반응 1만2천703건↑…사망 32명↑인과성 미확인": "http://www.yna.co.kr/view/AKR20210918025900530?section=safe/news"
}