{
	"LSK 글로벌 PS, 중국 시노백 코로나19 백신 임상 수행": "http://www.yna.co.kr/view/AKR20200901054600017?section=safe/news",
	"태백시 다수 밀집시설 방역수칙 준수 집중 점검": "http://www.yna.co.kr/view/AKR20200901052300062?section=safe/news",
	"코로나19 확진 한화 신정락 접촉한 서산 숙소 동료 40명 음성(종합)": "http://www.yna.co.kr/view/AKR20200901035151063?section=safe/news",
	"대전 한 교회 신도 8명 코로나19 집단감염…전날 목사도 확진": "http://www.yna.co.kr/view/AKR20200901037600063?section=safe/news",
	"코로나19 위중·중증환자 104명…2주 만에 11.6배로 급증 비상": "http://www.yna.co.kr/view/AKR20200901049000530?section=safe/news",
	"대구 확진자 2명 추가…사랑의교회 신도 37명째": "http://www.yna.co.kr/view/AKR20200901052000053?section=safe/news",
	"부산 2명 추가 확진…오피스텔 연관 감염 또 1명 나와": "http://www.yna.co.kr/view/AKR20200901051700051?section=safe/news",
	"\"코로나19 극복할 기계 만들어요\" 온라인 과학 꿈나무 대회": "http://www.yna.co.kr/view/AKR20200901051300063?section=safe/news",
	"[3보] 신규확진 235명, 누적 2만명 넘어서…소폭 감소세속 중환자 급증": "http://www.yna.co.kr/view/AKR20200901043751530?section=safe/news",
	"스페인 코로나19 재유행 진앙되나…\"확산속도, 독일의 10배\"": "http://www.yna.co.kr/view/AKR20200901050200009?section=safe/news",
	"부산 유치원·초중고 대부분 개학…밀집도 낮춰 등교수업": "http://www.yna.co.kr/view/AKR20200901050900051?section=safe/news",
	"삼성 폴란드 가전공장 직원 1명 코로나 확진 …\"공장 정상 가동\"": "http://www.yna.co.kr/view/AKR20200901047200003?section=safe/news",
	"삼척시 방문판매업체 코로나19 방역 관리 실태 점검": "http://www.yna.co.kr/view/AKR20200901045200062?section=safe/news",
	"서울 반포동 50대 주민 부천서 코로나19 확진": "http://www.yna.co.kr/view/AKR20200901047500065?section=safe/news",
	"전국 무용제 잠정 연기…코로나19 확산 속 안전 고려": "http://www.yna.co.kr/view/AKR20200901042400062?section=safe/news",
	"[속보] 코로나19 위·중증환자 104명…연일 급증 비상": "http://www.yna.co.kr/view/AKR20200901046300530?section=safe/news",
	"[2보] 코로나19 어제 235명 신규확진…누적 2만명 넘어서": "http://www.yna.co.kr/view/AKR20200901043700530?section=safe/news",
	"[1보] 코로나19 어제 235명 신규확진…누적 2만명 넘어서": "http://www.yna.co.kr/view/AKR20200901043500530?section=safe/news",
	"김강립 \"코로나19 중증환자 급증…상황 관리 매우 어렵다\"": "http://www.yna.co.kr/view/AKR20200901041000530?section=safe/news",
	"한화그룹, 거리두기 3단계 선제 시행…전 계열사 교차 재택": "http://www.yna.co.kr/view/AKR20200901039200003?section=safe/news",
	"코로나19 확진 한화이글스 신정락 접촉 40명 음성": "http://www.yna.co.kr/view/AKR20200901035100063?section=safe/news",
	"항공과학축제 '스페이스 챌린지', 코로나로 41년 만에 첫 취소": "http://www.yna.co.kr/view/AKR20200901034000504?section=safe/news",
	"경북서 광화문 집회 관련 3명 등 9명 코로나19 추가 확진": "http://www.yna.co.kr/view/AKR20200901031000053?section=safe/news",
	"기재차관 \"실물경제 위축 불가피…코로나 비상경제대책 보강\"": "http://www.yna.co.kr/view/AKR20200901030900002?section=safe/news",
	"\"코로나가 집값 잡겠다\"…코로나 재확산에 부동산 거래 위축": "http://www.yna.co.kr/view/AKR20200901026800003?section=safe/news",
	"광주·전남 집단감염 여파 계속…5명 추가 확진": "http://www.yna.co.kr/view/AKR20200901028400054?section=safe/news",
	"[2021예산] 코로나19 위기 극복 어촌·어항 인프라지원에 8천195억원": "http://www.yna.co.kr/view/AKR20200831159900530?section=safe/news",
	"경찰청 본청 1명 추가 확진에 10층 폐쇄…누적 총 3명": "http://www.yna.co.kr/view/AKR20200901028200004?section=safe/news",
	"주간보호센터 90대 확진자의 40대 손주도 양성…충북 129번째": "http://www.yna.co.kr/view/AKR20200901023300064?section=safe/news",
	"'코로나 충격' 2분기 성장률 -3.2%…속보치보다 0.1%p↑": "http://www.yna.co.kr/view/AKR20200901019500002?section=safe/news"
}