{
	"미 시카고 흑인 정치인, 마스크 쓰고 쇼핑 갔다가 불심검문 수모": "http://www.yna.co.kr/view/AKR20200507007600009?section=safe/news",
	"코로나19 치료비…위중 7천만원, 중증 1천200만원, 경증 478만원": "http://www.yna.co.kr/view/AKR20200506133800017?section=safe/news",
	"사흘만에 지역감염 발생 '긴장'…\"코로나19 '은밀한 전파' 우려\"": "http://www.yna.co.kr/view/AKR20200506136800017?section=safe/news",
	"미 지방의원 \"얼굴은 하나님의 형상\"…'노 마스크' 선언": "http://www.yna.co.kr/view/AKR20200507006700075?section=safe/news",
	"미 뉴욕주, 코로나19 입원 환자 84% '출퇴근 없이도' 감염": "http://www.yna.co.kr/view/AKR20200507006500072?section=safe/news",
	"마스크 없이 고글만 썼던 트럼프 \"마스크 썼다…뒤에서\"": "http://www.yna.co.kr/view/AKR20200507006400071?section=safe/news",
	"폼페이오 \"우한연구소 유래설 확신은 없어\" 한발빼…\"상당 증거\"(종합2보)": "http://www.yna.co.kr/view/AKR20200506176352071?section=safe/news",
	"코로나19 둔화한 유럽, 완화책 잇달아…경제 전망은 우울": "http://www.yna.co.kr/view/AKR20200507006300088?section=safe/news",
	"교황 \"코로나19 위기에도 노동자 존엄 지켜져야\"(종합)": "http://www.yna.co.kr/view/AKR20200506173151109?section=safe/news",
	"프랑스 상원 \"한국은 코로나19 모범사례\" 보고서": "http://www.yna.co.kr/view/AKR20200507005400081?section=safe/news",
	"국제간호협의회 \"코로나19 감염 의료 종사자, 최소 9만명\"": "http://www.yna.co.kr/view/AKR20200507005500088?section=safe/news",
	"코로나19에 공유경제 시련의 계절…우버·에어비엔비 감원 폭풍": "http://www.yna.co.kr/view/AKR20200507004400091?section=safe/news",
	"영국 코로나19 사망자 3만명 넘어…유럽서 처음": "http://www.yna.co.kr/view/AKR20200507004500085?section=safe/news",
	"체코 당국 \"코로나19 면역인구 4∼5%\"": "http://www.yna.co.kr/view/AKR20200507004000082?section=safe/news",
	"이탈리아서 코로나19 누적 완치자＞실질 감염자…사상 첫 추월": "http://www.yna.co.kr/view/AKR20200507003400109?section=safe/news",
	"\"트럼프 사위가 꾸린 자원봉사팀, 코로나19 의료공급 악화시켜\"": "http://www.yna.co.kr/view/AKR20200507002300071?section=safe/news",
	"[유럽증시] 코로나19로 경기침체 전망에 대부분 하락": "http://www.yna.co.kr/view/AKR20200507003100088?section=safe/news",
	"프랑스, 코로나19로 일감 끊긴 예술인들도 보조금 지급": "http://www.yna.co.kr/view/AKR20200507002400081?section=safe/news",
	"WHO \"코로나19 기원 조사 위한 전문가팀 방중 논의중\"": "http://www.yna.co.kr/view/AKR20200507002600088?section=safe/news",
	"미국인 코로나19사태 인식, 지지 정당 따라 현격한 차이": "http://www.yna.co.kr/view/AKR20200507001400072?section=safe/news",
	"메르켈 \"접촉제한 내달 5일까지…분데스리가 5월 중순 재개\"(종합)": "http://www.yna.co.kr/view/AKR20200507000451082?section=safe/news",
	"터키 보건장관 \"코로나와 싸움 첫 단계 완료…새 국면 접어들어\"": "http://www.yna.co.kr/view/AKR20200507001900108?section=safe/news",
	"축소·해산 거론 하루만에…트럼프 \"코로나19 TF 무기한 유지\"": "http://www.yna.co.kr/view/AKR20200507001800071?section=safe/news",
	"폼페이오, 우한연구소 유래설 \"확실성 없지만 상당한 증거 있어\"(종합)": "http://www.yna.co.kr/view/AKR20200506176351071?section=safe/news",
	"중국 \"코로나19 기원 조사팀 방중, 팬데믹 패배 뒤에야\"": "http://www.yna.co.kr/view/AKR20200507001500088?section=safe/news",
	"\"스웨덴 코로나19 사망자 3천명 근접\"": "http://www.yna.co.kr/view/AKR20200507000500098?section=safe/news",
	"메르켈 \"접촉제한 내달 5일까지…분데스리가 5월 중순 재개\"": "http://www.yna.co.kr/view/AKR20200507000400082?section=safe/news",
	"러시아 코로나19 감염자 프랑스·독일 규모 근접…\"16만5천여명\"(종합)": "http://www.yna.co.kr/view/AKR20200506152851080?section=safe/news",
	"코로나19 타격 차량공유업체 잇단 감원…우버 3천700명 일시해고": "http://www.yna.co.kr/view/AKR20200506176600072?section=safe/news",
	"'코로나19 중대발견' 앞둔 중국계 미국 교수, 의문의 총격사망": "http://www.yna.co.kr/view/AKR20200506175300072?section=safe/news"
}