{
	"부산 요양병원 간병인·입원환자 등 3명 추가 확진": "http://www.yna.co.kr/view/AKR20201021086700051?section=safe/news",
	"고위험시설 점검 돌입…\"방역수칙 한번만 어겨도 즉시 영업중단\"": "http://www.yna.co.kr/view/AKR20201021084000530?section=safe/news",
	"서울 관악구 수영장서 2명 감염…어제 17명 확진(종합)": "http://www.yna.co.kr/view/AKR20201021073851004?section=safe/news",
	"중국 코로나 이후 첫 '11·11 쇼핑축제'…'소비의 힘' 보여줄까": "http://www.yna.co.kr/view/AKR20201021079800089?section=safe/news",
	"OECD 사무총장 \"코로나19보다 경제 영향이 더 오래갈 것\"": "http://www.yna.co.kr/view/AKR20201021070100009?section=safe/news",
	"\"코로나19 따른 국제교류 중단 위기 비대면으로 돌파구\"": "http://www.yna.co.kr/view/AKR20201021073200062?section=safe/news",
	"인천서 자가격리자 등 5명 양성 판정…지역 누적 1천10명(종합)": "http://www.yna.co.kr/view/AKR20201021074951065?section=safe/news",
	"[속보] \"클럽·헌팅포차 등서 집단감염 발생시 영업제한 조치 추가\"": "http://www.yna.co.kr/view/AKR20201021080100530?section=safe/news",
	"[속보] \"고위험시설 핵심방역수칙 1회만 위반해도 즉시 영업중단·벌금\"": "http://www.yna.co.kr/view/AKR20201021076900530?section=safe/news",
	"서울 관악구 수영장서 2명 감염…어제 17명 확진": "http://www.yna.co.kr/view/AKR20201021073800004?section=safe/news",
	"[속보] \"2주간 요양병원·요양시설·정신폐쇄병동 8천여곳 방역 점검\"": "http://www.yna.co.kr/view/AKR20201021076000530?section=safe/news",
	"인천서 자가격리자 등 4명 양성 판정…지역 누적 1천9명": "http://www.yna.co.kr/view/AKR20201021074900065?section=safe/news",
	"'서울 확진자 접촉' 정읍 시민 2명 코로나19 감염(종합)": "http://www.yna.co.kr/view/AKR20201021032751055?section=safe/news",
	"[속보] \"코로나19·독감 동시검사 진단도구 11월까지 도입…건보 적용\"": "http://www.yna.co.kr/view/AKR20201021075600530?section=safe/news",
	"미국서 코로나19 확진 30대 여성 기내서 숨져": "http://www.yna.co.kr/view/AKR20201021066200009?section=safe/news",
	"[속보] 정부 \"수도권 신규확진자 확실히 줄지 않아 여전히 불안\"": "http://www.yna.co.kr/view/AKR20201021073600530?section=safe/news",
	"인니, 코로나에도 내년 5∼6월 U-20 월드컵 개최 원해": "http://www.yna.co.kr/view/AKR20201021068200104?section=safe/news",
	"수젠텍, 코로나19 항원신속진단키트 독일 판매 개시": "http://www.yna.co.kr/view/AKR20201021064400017?section=safe/news",
	"코로나로 멈춘 부산대역 '불금버스킹' 하반기 공연 재개": "http://www.yna.co.kr/view/AKR20201021061000051?section=safe/news",
	"제넥신 코로나19 백신 임상에 정부 연구비 93억원 지원": "http://www.yna.co.kr/view/AKR20201021060800017?section=safe/news",
	"경기도 신규 확진 24명…부천 노인주간보호센터서도 집단감염": "http://www.yna.co.kr/view/AKR20201021059000061?section=safe/news",
	"부산 신규확진 1명 경로 불분명…자가격리 이탈도 1명 적발": "http://www.yna.co.kr/view/AKR20201021058600051?section=safe/news",
	"코로나19 감염시키고 지켜본다…영국, 논란 속 실험 강행키로": "http://www.yna.co.kr/view/AKR20201021051900009?section=safe/news",
	"코로나19 세계적 유행에 해외유입 다시 30명대…7월말 이후 최다": "http://www.yna.co.kr/view/AKR20201021042600530?section=safe/news",
	"청주 40대 코로나19 확진…자녀 다니는 초등학교 등교중지(종합)": "http://www.yna.co.kr/view/AKR20201021023351064?section=safe/news",
	"감염병병원 37.5% \"중증 코로나 환자 상급병원 이송 어려워\"": "http://www.yna.co.kr/view/AKR20201021052300017?section=safe/news",
	"홍콩 캐세이퍼시픽 \"코로나에 5천900명 감원\"": "http://www.yna.co.kr/view/AKR20201021054200074?section=safe/news",
	"확진 아내 돌보던 남편도 양성…광주 SRC재활병원 관련": "http://www.yna.co.kr/view/AKR20201021049600061?section=safe/news",
	"신규확진 91명 세 자릿수 육박…해외유입 34명, 84일만에 최다(종합)": "http://www.yna.co.kr/view/AKR20201021029851530?section=safe/news",
	"[3보] 신규확진 91명 세 자릿수 육박…해외유입 34명, 84일만에 최다": "http://www.yna.co.kr/view/AKR20201021029800530?section=safe/news"
}