{
	"\"입국자 격리 거부시 고발\" 광주·전남 생활치료센터 보강(종합)": "http://www.yna.co.kr/view/AKR20200401099451054?section=safe/news",
	"여성기업 94% \"코로나19로 피해…여성 경영인으로 불안\"": "http://www.yna.co.kr/view/AKR20200401144000030?section=safe/news",
	"영국 13세 소년 코로나19로 사망…\"현재 청소년 치명률 0.006%\"": "http://www.yna.co.kr/view/AKR20200401138900009?section=safe/news",
	"코로나19에 '혈장치료' 개시…세브란스병원서 중증 3명에 투여": "http://www.yna.co.kr/view/AKR20200401141600017?section=safe/news",
	"경기도 누적확진자 500명 넘어…병원 집단감염에 해외유입 지속": "http://www.yna.co.kr/view/AKR20200401143100061?section=safe/news",
	"확진자 접촉 후 음성이었다가 자가격리 해제 전 검사서 확진": "http://www.yna.co.kr/view/AKR20200401138700004?section=safe/news",
	"목포시 해외 입국자 관리 강화…28실 규모 격리시설 운영": "http://www.yna.co.kr/view/AKR20200401140800054?section=safe/news",
	"내달 예정 '평화·번영 제주포럼', 코로나19 여파 11월로 연기": "http://www.yna.co.kr/view/AKR20200401141400056?section=safe/news",
	"대만, 코로나19 대응 43조원 경기부양책 공개": "http://www.yna.co.kr/view/AKR20200401140000009?section=safe/news",
	"대구 한사랑요양병원도 확진자 대남병원 넘어서…121명(종합2보)": "http://www.yna.co.kr/view/AKR20200401056252053?section=safe/news",
	"미국·캐나다서 입국한 2명 양성…수원시 확진자 총 44명": "http://www.yna.co.kr/view/AKR20200401140100061?section=safe/news",
	"인천 첫 공무원 확진자 발생…소속 군청 한때 '비상'": "http://www.yna.co.kr/view/AKR20200401139400065?section=safe/news",
	"은혜 갚은 중국 옥환시, 당진시에 마스크 5천개 기증": "http://www.yna.co.kr/view/AKR20200401137100063?section=safe/news",
	"경산 서요양병원 확진 70대 사망…국내 167명": "http://www.yna.co.kr/view/AKR20200401138000053?section=safe/news",
	"고령군 코로나19로 어려운 중소기업에 융자 이자 지원": "http://www.yna.co.kr/view/AKR20200401129100053?section=safe/news",
	"\"서울아산병원 '확진자 접촉' 입원환자 43명 코호트 격리\"(종합)": "http://www.yna.co.kr/view/AKR20200401120851017?section=safe/news",
	"코로나19에 위축 경기 살린다…청송사랑화폐 10% 특별 할인": "http://www.yna.co.kr/view/AKR20200401132600053?section=safe/news",
	"코로나19 집중 대응에 차질 생길라…광주시 핵심 현안 점검": "http://www.yna.co.kr/view/AKR20200401128400054?section=safe/news",
	"사우디 메카 정기 성지순례도 코로나19에 취소 가능성 커": "http://www.yna.co.kr/view/AKR20200401123100111?section=safe/news",
	"\"어려운 이웃 동생들에게 주세요\" 마스크 16장 기탁한 중학생": "http://www.yna.co.kr/view/AKR20200401121700062?section=safe/news",
	"\"서울아산병원 '확진자 접촉' 입원환자 43명 코호트 격리\"": "http://www.yna.co.kr/view/AKR20200401120800017?section=safe/news",
	"미국 국무부 해외 현지 직원 2명, 코로나19로 사망": "http://www.yna.co.kr/view/AKR20200401121200009?section=safe/news",
	"주한미군 평택기지서 이틀 만에 코로나19 확진…14번째": "http://www.yna.co.kr/view/AKR20200401120100504?section=safe/news",
	"경기도·사회복지모금회, 코로나19 성금 12억 취약계층에 지원": "http://www.yna.co.kr/view/AKR20200401119100061?section=safe/news",
	"코로나19 대응 단톡방에 음란 동영상 올린 50대 공무원": "http://www.yna.co.kr/view/AKR20200401119300065?section=safe/news",
	"EDGC \"솔젠트, 코로나19 진단키트 필리핀·미얀마 공급\"": "http://www.yna.co.kr/view/AKR20200401118400017?section=safe/news",
	"제약바이오 38개 기업, 코로나19 극복 구호품·성금 55억원 지원": "http://www.yna.co.kr/view/AKR20200401118100017?section=safe/news",
	"한적 전북지사, 자가격리자용 긴급구호품 400세트 추가제작": "http://www.yna.co.kr/view/AKR20200401117600055?section=safe/news",
	"의정부성모병원 환자 2명 코로나19 추가 확진…총 12명": "http://www.yna.co.kr/view/AKR20200401116100060?section=safe/news",
	"제주도, 자가격리 거부 국외방문 4명에 출도 조치": "http://www.yna.co.kr/view/AKR20200401105800056?section=safe/news"
}