{
	"\"코로나19 여파로 휴가는 호텔보다 펜션, 도심보다 교외\"": "http://www.yna.co.kr/view/AKR20200610067400030?section=safe/news",
	"강원도, 코로나19 피해 극복 지방세 감면…29억원 규모 예상": "http://www.yna.co.kr/view/AKR20200610068600062?section=safe/news",
	"송파 강남대성학원 \"학생·강사 등 471명 코로나19 전원 음성\"": "http://www.yna.co.kr/view/AKR20200610069500530?section=safe/news",
	"\"테슬라 미국 공장서 코로나19 확진자 발생\" 주장 나와": "http://www.yna.co.kr/view/AKR20200610063200009?section=safe/news",
	"코로나 확산에 中 해외 온라인 판매 '날개'…자전거 최대 20배↑": "http://www.yna.co.kr/view/AKR20200610061300083?section=safe/news",
	"자가격리 장소 거짓 신고…위치추적해 격리시설 강제이송": "http://www.yna.co.kr/view/AKR20200610066400051?section=safe/news",
	"경남도, 코로나 피해 어업인에게 양식재해보험 지원 확대": "http://www.yna.co.kr/view/AKR20200610057200052?section=safe/news",
	"코로나19 확산에도 전 세계 경제활동 재개 '우격다짐'": "http://www.yna.co.kr/view/AKR20200610065100009?section=safe/news",
	"미국 최고권위자 \"코로나19 이제 시작이며 종식 멀었다\"": "http://www.yna.co.kr/view/AKR20200610047500009?section=safe/news",
	"확진자 동선 공개 '사생활 침해' 논란 없앤다…KAIST 앱 개발": "http://www.yna.co.kr/view/AKR20200610055300063?section=safe/news",
	"[속보] 송파 강남대성학원 \"코로나19 검진 471명 전원 음성\"": "http://www.yna.co.kr/view/AKR20200610064800530?section=safe/news",
	"과천 안보지원사 코로나19 확진자 4명 추가…부대원 전수검사": "http://www.yna.co.kr/view/AKR20200610056251504?section=safe/news",
	"신규확진 사흘만에 다시 50명대…탁구장-리치웨이 감염 확산일로(종합)": "http://www.yna.co.kr/view/AKR20200610058751530?section=safe/news",
	"[2보] 신규확진 사흘만에 다시 50명대…탁구장-리치웨이 감염 확산일로": "http://www.yna.co.kr/view/AKR20200610058700530?section=safe/news",
	"알리바바 클라우드, '포스트 코로나' 대비해 인재 5천명 충원": "http://www.yna.co.kr/view/AKR20200610055900009?section=safe/news",
	"[속보] 50명중 41명 수도권…탁구장-리치웨이발 'n차 감염' 확산 여파": "http://www.yna.co.kr/view/AKR20200610057400530?section=safe/news",
	"[1보] 코로나19 어제 50명 신규확진…사흘만에 다시 50명대 증가": "http://www.yna.co.kr/view/AKR20200610057300530?section=safe/news",
	"[속보] 과천 안보지원사서 4명 코로나19 추가 확진…총 5명": "http://www.yna.co.kr/view/AKR20200610056200504?section=safe/news",
	"[속보] 롯데월드 방문 원묵고 3학년생, 코로나19 '음성' 최종 판정": "http://www.yna.co.kr/view/AKR20200610055100530?section=safe/news",
	"日아소 '코로나 사망 국민 수준론' 논란…근거 수치도 오류": "http://www.yna.co.kr/view/AKR20200610047400073?section=safe/news",
	"미중 갈등 속 駐우한 미국 총영사관, 22일께 업무 재개": "http://www.yna.co.kr/view/AKR20200610046700083?section=safe/news",
	"\"코로나19에 올해 폐업 미국 소매점 2만5천개에 달할 듯\"": "http://www.yna.co.kr/view/AKR20200610046000009?section=safe/news",
	"\"코로나19 바이러스 핸드폰에 오래 남아있어…자주 닦아야\"": "http://www.yna.co.kr/view/AKR20200603029300017?section=safe/news",
	"인천서 2명 추가 확진…서울 마곡동 콜센터·미용실 근무자 양성": "http://www.yna.co.kr/view/AKR20200610042900065?section=safe/news",
	"수원 영통구 70대 여성 코로나19 확진…리치웨이발 감염 추정": "http://www.yna.co.kr/view/AKR20200610042600061?section=safe/news",
	"중국 코로나19 신규 확진 해외 역유입만 3명": "http://www.yna.co.kr/view/AKR20200610035300083?section=safe/news",
	"\"코로나로 지친 의료진에 미술로 치유\"…병원에 미술품 전시": "http://www.yna.co.kr/view/AKR20200610037100005?section=safe/news",
	"정몽구재단 \"의료진 위한 코로나19 정보 앱 호평\"": "http://www.yna.co.kr/view/AKR20200610034400003?section=safe/news",
	"식약처, 제약업체 코로나19 치료용 한약 제제 개발 돕는다": "http://www.yna.co.kr/view/AKR20200609170100017?section=safe/news",
	"대전지검, 코로나19 확산 방지 역행 31명 기소…80명 수사 중": "http://www.yna.co.kr/view/AKR20200610022500063?section=safe/news"
}