{
	"아스트라제네카 백신 유럽공급 차질 \"국내 1분기 도입 변동없어\"": "http://www.yna.co.kr/view/AKR20210124025900530?section=safe/news",
	"스페인 장성 '백신 새치기' 들통나 군복 벗어": "http://www.yna.co.kr/view/AKR20210124024600009?section=safe/news",
	"대구서 신규 확진 12명…스크린골프장 관련 누적 15명(종합)": "http://www.yna.co.kr/view/AKR20210124020751053?section=safe/news",
	"충북서 가족간 감염 이어져…청주·충주 6명 확진": "http://www.yna.co.kr/view/AKR20210124024400064?section=safe/news",
	"대만 '방역 모범'도 옛말…코로나 격리 967명으로 사상 최대": "http://www.yna.co.kr/view/AKR20210124023500009?section=safe/news",
	"제주서 코로나19 신규 확진 2명…누적 518명": "http://www.yna.co.kr/view/AKR20210124023200056?section=safe/news",
	"군산 미 공군 확진자 5명으로 늘어…2천500여명 전수검사": "http://www.yna.co.kr/view/AKR20210124022200055?section=safe/news",
	"코로나에도 중국 작년 외화보유액 1086억달러 늘었다": "http://www.yna.co.kr/view/AKR20210124023000083?section=safe/news",
	"대구서 신규 확진 12명…스크린골프장 관련 누적 15명": "http://www.yna.co.kr/view/AKR20210124020700053?section=safe/news",
	"인천서 코로나19 확진 11명 추가…1명 사망": "http://www.yna.co.kr/view/AKR20210124021300065?section=safe/news",
	"서울 신규확진 133명…17일째 100명대 유지하며 등락(종합)": "http://www.yna.co.kr/view/AKR20210124013851004?section=safe/news",
	"코로나로 임금 불평등 심화…현정부 들어 임금 지니계수 첫 상승": "http://www.yna.co.kr/view/AKR20210124020500530?section=safe/news",
	"우한 봉쇄 1년 지났는데…중국은 '다시 코로나와 전쟁'": "http://www.yna.co.kr/view/AKR20210124020600083?section=safe/news",
	"'방역 모범국' 뉴질랜드 \"코로나19 지역감염 조사 중\"": "http://www.yna.co.kr/view/AKR20210124018100009?section=safe/news",
	"경남 신규 확진자 6명 추가…모두 60대 이상 고령": "http://www.yna.co.kr/view/AKR20210124018800052?section=safe/news",
	"경기북부경찰청 800여명 전수조사…추가 확진 없어": "http://www.yna.co.kr/view/AKR20210124018400060?section=safe/news",
	"다시 300명대, 1주간 일평균 지역발생 365명…거리두기 조정되나(종합)": "http://www.yna.co.kr/view/AKR20210123042251530?section=safe/news",
	"울산서 기존 확진자 가족 2명 코로나19 감염": "http://www.yna.co.kr/view/AKR20210124017400057?section=safe/news",
	"경기 어제 99명 확진…54일 만에 100명 아래로": "http://www.yna.co.kr/view/AKR20210124015300061?section=safe/news",
	"홍콩 1만명 봉쇄한 날 코로나 누적환자 1만명 넘어": "http://www.yna.co.kr/view/AKR20210124014000074?section=safe/news",
	"부산서 코로나19 확진자 4명 추가…감염경로 조사 중": "http://www.yna.co.kr/view/AKR20210124014500051?section=safe/news",
	"KT, 인공지능 기반 감염병 대응 연구 본격화…SHINE 앱 출시": "http://www.yna.co.kr/view/AKR20210124012700017?section=safe/news",
	"신규확진 392명, 주말 영향 다시 300명대로…사망자 12명 늘어(종합)": "http://www.yna.co.kr/view/AKR20210124009151530?section=safe/news",
	"서울 신규확진 133명…17일째 100명대 유지하며 등락": "http://www.yna.co.kr/view/AKR20210124013800004?section=safe/news",
	"수도권 임시검사소 익명검사 62명 확진…수도권 지역발생의 25%": "http://www.yna.co.kr/view/AKR20210124013400530?section=safe/news",
	"[3보] 신규확진 392명, 주말 영향 다시 300명대로…사망자 12명 늘어": "http://www.yna.co.kr/view/AKR20210124009100530?section=safe/news",
	"\"영국, 코로나 고위험국 입국자들 '호텔 격리' 검토 중\"": "http://www.yna.co.kr/view/AKR20210124010900009?section=safe/news",
	"[속보] 코로나19로 어제 12명 사망…누적 1천349명": "http://www.yna.co.kr/view/AKR20210124012000530?section=safe/news",
	"[2보] 코로나19 어제 392명 신규확진…다시 300명대로": "http://www.yna.co.kr/view/AKR20210124009000530?section=safe/news",
	"[1보] 코로나19 어제 392명 신규확진…다시 300명대로": "http://www.yna.co.kr/view/AKR20210124008800530?section=safe/news"
}