{
	"가평서 80대 확진자의 남편·아들 감염": "http://www.yna.co.kr/view/AKR20200822034700060?section=safe/news",
	"김포 주민 2명 코로나19 확진…지역 누적 89명": "http://www.yna.co.kr/view/AKR20200822034400065?section=safe/news",
	"코로나바이러스, 서부로랜드고릴라 등 멸종위기종도 감염 위협": "http://www.yna.co.kr/view/AKR20200822034300009?section=safe/news",
	"분당차병원 암센터 환자 1명 확진…진료 전면 중단(종합)": "http://www.yna.co.kr/view/AKR20200822025351061?section=safe/news",
	"코로나 재확산 필리핀, 대중교통 이어 쇼핑몰도 얼굴가리개 의무": "http://www.yna.co.kr/view/AKR20200822034100076?section=safe/news",
	"광주시장·시의장·교육감 코로나 검사…수행비서, 확진자 접촉": "http://www.yna.co.kr/view/AKR20200822033800054?section=safe/news",
	"26일부터 수도권 외 유·초·중 1/3 등교, 고교는 2/3 등교": "http://www.yna.co.kr/view/AKR20200822033200530?section=safe/news",
	"대구 광화문 방문 포함 확진자 6명 늘어": "http://www.yna.co.kr/view/AKR20200822033100053?section=safe/news",
	"원주 유치원 교사와 여행한 친척 등 10명 무더기 확진": "http://www.yna.co.kr/view/AKR20200822032700062?section=safe/news",
	"與, 정은경 면담 김종인에 \"질본까지 감염될라\"\"셀프 대선행보\"": "http://www.yna.co.kr/view/AKR20200822032800001?section=safe/news",
	"바이든 \"코로나19 차단 위해 필요하다면 봉쇄정책 취할 것\"": "http://www.yna.co.kr/view/AKR20200822032100009?section=safe/news",
	"사회적 거리두기 2단계 전국 확대…스포츠도 전 경기 무관중": "http://www.yna.co.kr/view/AKR20200822032500007?section=safe/news",
	"[속보] 이용섭 광주시장·시의장 코로나19 검사": "http://www.yna.co.kr/view/AKR20200822032400054?section=safe/news",
	"서울아산병원 간호사 코로나19 확진…병동 일부 폐쇄(종합)": "http://www.yna.co.kr/view/AKR20200822031051004?section=safe/news",
	"내일부터 사회적 거리두기 2단계 전국 확대…\"코로나 상황 위태\"(종합)": "http://www.yna.co.kr/view/AKR20200822029151530?section=safe/news",
	"수원 거주 60대 확진…안양의 금식기도원서 감염 추정": "http://www.yna.co.kr/view/AKR20200822031800061?section=safe/news",
	"한진중공업 영도조선소 현장 직원 2명 추가 확진": "http://www.yna.co.kr/view/AKR20200822031100051?section=safe/news",
	"경남 코로나19 확진 5명…광복절 집회 교회 '비대면 예배' 명령": "http://www.yna.co.kr/view/AKR20200822030400052?section=safe/news",
	"서울아산병원 간호사 확진…병동 일부 폐쇄": "http://www.yna.co.kr/view/AKR20200822031000004?section=safe/news",
	"중국 옌지서 대구발 코로나 무증상 감염자 나와(종합)": "http://www.yna.co.kr/view/AKR20200822029000083?section=safe/news",
	"전주 50대 코로나19 확진…전북 67번째": "http://www.yna.co.kr/view/AKR20200822029300055?section=safe/news",
	"광화문집회 참석한 노부부의 딸·사위·손녀 확진": "http://www.yna.co.kr/view/AKR20200822030200060?section=safe/news",
	"코로나19 재확산 와중에 대관령서 전국 마라톤대회": "http://www.yna.co.kr/view/AKR20200822028800062?section=safe/news",
	"코로나로 힘든데…태국 8천500억 中잠수함 구매추진에 \"열 받네\"": "http://www.yna.co.kr/view/AKR20200822030600076?section=safe/news",
	"캐나다 6월 소매, 전월보다 23% 증가…코로나 전 수준": "http://www.yna.co.kr/view/AKR20200822028200009?section=safe/news",
	"[속보] \"코로나19 대응보다 중요한 일 없어…힘 모아 위기 극복해야\"": "http://www.yna.co.kr/view/AKR20200822029600530?section=safe/news",
	"[속보] \"집단감염 발생 지역 학교는 원격수업 전환…26일부터 적용\"": "http://www.yna.co.kr/view/AKR20200822029800530?section=safe/news",
	"내일부터 사회적 거리두기 2단계 전국 확대…\"코로나 상황 위태\"": "http://www.yna.co.kr/view/AKR20200822029100530?section=safe/news",
	"코로나19 재확산 아랑곳 제주 여름 막바지 관광객 '북적'": "http://www.yna.co.kr/view/AKR20200822028400056?section=safe/news",
	"홍남기 \"의료계, 코로나19 극복 위해 파업 철회해 달라\"": "http://www.yna.co.kr/view/AKR20200822026600002?section=safe/news"
}